test_cb_tdqq/__init__.py
test_cb_tdqq/dataloader.py
test_cb_tdqq/training.py
test_cb_tdqq/utils.py
test_cb_tdqq/choosing_negatives/__init__.py
test_cb_tdqq/choosing_negatives/choosing_hard_negatives.py
test_cb_tdqq/choosing_negatives/choosing_random_negatives.py
test_cb_tdqq/embedding/__init__.py
test_cb_tdqq/embedding/colbert_embedding.py
test_cb_tdqq/embedding/sbert_embedding.py
test_cb_tdqq/evaluating/__init__.py
test_cb_tdqq/evaluating/ir_eval.py
test_cb_tdqq/indexing/__init__.py
test_cb_tdqq/indexing/bm25/__init__.py
test_cb_tdqq/indexing/bm25/bm_25.py
test_cb_tdqq/indexing/faiss/HNSW_faiss_index.py
test_cb_tdqq/indexing/faiss/IVF_faiss_index.py
test_cb_tdqq/indexing/faiss/__init__.py
test_cb_tdqq/indexing/faiss/base_faiss_index.py
test_cb_tdqq/indexing/faiss/flat_faiss_index.py
test_cb_tdqq/reranking/__init__.py
test_cb_tdqq/reranking/colbert_batch_reranker.py
test_cb_tdqq/retrieving/__init__.py
test_cb_tdqq/retrieving/bm25_search.py
test_cb_tdqq/retrieving/colbert_search_faiss.py
test_cb_tdqq/retrieving/faiss_search.py
test_cb_tdqq-0.0.4.dist-info/licenses/LICENSE
test_cb_tdqq-0.0.4.dist-info/METADATA
test_cb_tdqq-0.0.4.dist-info/WHEEL
test_cb_tdqq-0.0.4.dist-info/top_level.txt
test_cb_tdqq-0.0.4.dist-info/RECORD
